ghlang/__init__.py
ghlang/config.py
ghlang/exceptions.py
ghlang/github_client.py
ghlang/logging.py
ghlang/themes.py
ghlang/tokount_client.py
ghlang/visualizers.py
ghlang/cli/__init__.py
ghlang/cli/__main__.py
ghlang/cli/config.py
ghlang/cli/github.py
ghlang/cli/local.py
ghlang/cli/utils.py
ghlang/static/__init__.py
ghlang/static/default_config.toml
ghlang/static/lang_mapping.py
ghlang/static/themes.py
ghlang-2.4.1.dist-info/METADATA
ghlang-2.4.1.dist-info/WHEEL
ghlang-2.4.1.dist-info/entry_points.txt
ghlang-2.4.1.dist-info/licenses/LICENSE
ghlang-2.4.1.dist-info/RECORD
