Metadata-Version: 2.4
Name: ghlang
Version: 2.4.1
Summary: Generate language statistics and visualizations from GitHub repositories or local files
Project-URL: Homepage, https://github.com/MihaiStreames/ghlang
Project-URL: Repository, https://github.com/MihaiStreames/ghlang
Project-URL: Issues, https://github.com/MihaiStreames/ghlang/issues
Author-email: MihaiStreames <72852703+MihaiStreames@users.noreply.github.com>
License: MIT
License-File: LICENSE
Keywords: analytics,charts,cli,code-analysis,developer-tools,github,metrics,programming-languages,statistics,visualization
Classifier: Development Status :: 4 - Beta
Classifier: Environment :: Console
Classifier: Intended Audience :: Developers
Classifier: License :: OSI Approved :: MIT License
Classifier: Operating System :: OS Independent
Classifier: Programming Language :: Python :: 3
Classifier: Programming Language :: Python :: 3.10
Classifier: Programming Language :: Python :: 3.11
Classifier: Programming Language :: Python :: 3.12
Classifier: Programming Language :: Python :: 3.13
Classifier: Topic :: Software Development :: Libraries :: Python Modules
Classifier: Topic :: Software Development :: Quality Assurance
Classifier: Topic :: Utilities
Classifier: Typing :: Typed
Requires-Python: >=3.10
Requires-Dist: matplotlib>=3.10.8
Requires-Dist: pillow>=12.1.0
Requires-Dist: pyyaml>=6.0.3
Requires-Dist: requests>=2.32.5
Requires-Dist: rich>=14.2.0
Requires-Dist: typer>=0.21.1
Provides-Extra: dev
Requires-Dist: types-pyyaml>=6.0.12.20250915; extra == 'dev'
Requires-Dist: types-requests>=2.32.4.20260107; extra == 'dev'
